stash_ai_server/__init__.py
stash_ai_server/alembic.ini
stash_ai_server/dev_entrypoint.py
stash_ai_server/entrypoint.py
stash_ai_server/main.py
stash_ai_server/actions/__init__.py
stash_ai_server/actions/models.py
stash_ai_server/actions/registry.py
stash_ai_server/alembic/__init__.py
stash_ai_server/alembic/env.py
stash_ai_server/alembic/versions/0001_initial.py
stash_ai_server/alembic/versions/0002_recommendation_preferences.py
stash_ai_server/alembic/versions/0003_client_event_id_text.py
stash_ai_server/api/__init__.py
stash_ai_server/api/actions.py
stash_ai_server/api/interactions.py
stash_ai_server/api/plugins.py
stash_ai_server/api/recommendations.py
stash_ai_server/api/system.py
stash_ai_server/api/tasks.py
stash_ai_server/api/version.py
stash_ai_server/api/ws.py
stash_ai_server/core/__init__.py
stash_ai_server/core/api_key.py
stash_ai_server/core/compat.py
stash_ai_server/core/config.py
stash_ai_server/core/dependencies.py
stash_ai_server/core/logging_config.py
stash_ai_server/core/migrations.py
stash_ai_server/core/runtime.py
stash_ai_server/core/system_settings.py
stash_ai_server/db/__init__.py
stash_ai_server/db/ai_results_store.py
stash_ai_server/db/session.py
stash_ai_server/db/sqlite_fdw.py
stash_ai_server/db/sqlite_migrator.py
stash_ai_server/models/__init__.py
stash_ai_server/models/ai_results.py
stash_ai_server/models/interaction.py
stash_ai_server/models/plugin.py
stash_ai_server/models/recommendation.py
stash_ai_server/plugin_runtime/__init__.py
stash_ai_server/plugin_runtime/loader.py
stash_ai_server/plugin_runtime/settings_registry.py
stash_ai_server/recommendations/__init__.py
stash_ai_server/recommendations/models.py
stash_ai_server/recommendations/registry.py
stash_ai_server/recommendations/storage.py
stash_ai_server/recommendations/utils/__init__.py
stash_ai_server/recommendations/utils/pagination.py
stash_ai_server/recommendations/utils/scene_fetch.py
stash_ai_server/recommendations/utils/tag_profiles.py
stash_ai_server-0.9.2.dist-info/METADATA
stash_ai_server-0.9.2.dist-info/WHEEL
stash_ai_server-0.9.2.dist-info/entry_points.txt
stash_ai_server-0.9.2.dist-info/top_level.txt
stash_ai_server-0.9.2.dist-info/RECORD
