Metadata-Version: 2.4
Name: stash-ai-server
Version: 0.9.2
Summary: Stash AI Overhaul Backend Server
Author: Stash AI Overhaul
License: MIT
Project-URL: Homepage, https://github.com/skier233/Stash-AIServer
Requires-Python: >=3.12
Requires-Dist: fastapi==0.127.0
Requires-Dist: uvicorn[standard]==0.40.0
Requires-Dist: SQLAlchemy==2.0.45
Requires-Dist: alembic==1.17.2
Requires-Dist: psycopg[binary]==3.3.2
Requires-Dist: pgvector==0.4.2
Requires-Dist: pydantic==2.12.5
Requires-Dist: python-dotenv==1.2.1
Requires-Dist: httpx==0.28.1
Requires-Dist: stashapi==0.1.3
Requires-Dist: PyYAML==6.0.3
Requires-Dist: packaging==25.0
Provides-Extra: test
Requires-Dist: pytest>=7.0.0; extra == "test"
Requires-Dist: pytest-asyncio>=0.21.0; extra == "test"
Requires-Dist: pytest-timeout>=2.1.0; extra == "test"
Requires-Dist: pytest-mock>=3.10.0; extra == "test"
Requires-Dist: pytest-cov>=4.0.0; extra == "test"
Requires-Dist: hypothesis>=6.68.0; extra == "test"
Requires-Dist: asyncpg>=0.28.0; extra == "test"
